slumbernana/__init__.py
slumbernana/monkey.py
slumbernana-1.0.dist-info/METADATA
slumbernana-1.0.dist-info/WHEEL
slumbernana-1.0.dist-info/top_level.txt
slumbernana-1.0.dist-info/RECORD
