Metadata-Version: 2.1
Name: slumbernana
Version: 1.0
Summary: 你，知道「睡蕉小猴」嗎？ 什麼？你不知道？那你有福了蕉！
Author: 白狐不白
Author-email: shk3210a@gmail.com
Classifier: Programming Language :: Python :: 3
Classifier: License :: OSI Approved :: MIT License
Classifier: Operating System :: OS Independent
Requires-Python: >=3.6
